README.rst
setup.cfg
setup.py
MusicBoxApi/__init__.py
MusicBoxApi/api.py
MusicBoxApi/config.py
MusicBoxApi/const.py
MusicBoxApi/logger.py
MusicBoxApi/singleton.py
MusicBoxApi/storage.py
MusicBoxApi/utils.py
MusicBoxApi.egg-info/PKG-INFO
MusicBoxApi.egg-info/SOURCES.txt
MusicBoxApi.egg-info/dependency_links.txt
MusicBoxApi.egg-info/requires.txt
MusicBoxApi.egg-info/top_level.txt