Metadata-Version: 1.1
Name: MusicBoxApi
Version: 1.0.8
Summary: NetEase Music Api
Home-page: https://github.com/wzpan/MusicBoxApi
Author: wzpan
Author-email: m@hahack.com
License: MIT
Keywords: netEase music api python
Platform: UNKNOWN
Classifier: Development Status :: 3 - Alpha
Classifier: Intended Audience :: Developers
Classifier: Topic :: Software Development :: Libraries :: Python Modules
Classifier: License :: OSI Approved :: MIT License
Classifier: Programming Language :: Python :: 2
Classifier: Programming Language :: Python :: 2.6
Classifier: Programming Language :: Python :: 2.7
Classifier: Programming Language :: Python :: 3
Classifier: Programming Language :: Python :: 3.3
Classifier: Programming Language :: Python :: 3.4
Classifier: Programming Language :: Python :: 3.5
